setup.py
assoc_space/__init__.py
assoc_space/compat.py
assoc_space/eigenmath.py
assoc_space/util.py
assoc_space.egg-info/PKG-INFO
assoc_space.egg-info/SOURCES.txt
assoc_space.egg-info/dependency_links.txt
assoc_space.egg-info/requires.txt
assoc_space.egg-info/top_level.txt