Metadata-Version: 1.0
Name: assoc-space
Version: 1.0.2
Summary: Computes association strength over semantic networks in a dimensionality-reduced form.
Home-page: http://github.com/LuminosoInsight/assoc-space
Author: Luminoso Technologies, Inc.
Author-email: dev@luminoso.com
License: MIT
Platform: any
